utcp_mcp/__init__.py
utcp_mcp/mcp_call_template.py
utcp_mcp/mcp_communication_protocol.py
utcp_mcp-1.1.2.dist-info/METADATA
utcp_mcp-1.1.2.dist-info/WHEEL
utcp_mcp-1.1.2.dist-info/entry_points.txt
utcp_mcp-1.1.2.dist-info/top_level.txt
utcp_mcp-1.1.2.dist-info/RECORD
