Metadata-Version: 2.4
Name: utcp-mcp
Version: 1.1.2
Summary: UTCP communication protocol plugin for interoperability with the Model Context Protocol (MCP).
Author: UTCP Contributors
License-Expression: MPL-2.0
Project-URL: Homepage, https://utcp.io
Project-URL: Source, https://github.com/universal-tool-calling-protocol/python-utcp
Project-URL: Issues, https://github.com/universal-tool-calling-protocol/python-utcp/issues
Classifier: Development Status :: 4 - Beta
Classifier: Intended Audience :: Developers
Classifier: Programming Language :: Python :: 3
Classifier: Operating System :: OS Independent
Requires-Python: >=3.11
Requires-Dist: pydantic>=2.0
Requires-Dist: mcp>=1.12
Requires-Dist: utcp>=1.1
Requires-Dist: mcp-use>=1.3
Requires-Dist: langchain<0.4.0,>=0.3.27
Provides-Extra: dev
Requires-Dist: build; extra == "dev"
Requires-Dist: pytest; extra == "dev"
Requires-Dist: pytest-asyncio; extra == "dev"
Requires-Dist: pytest-cov; extra == "dev"
Requires-Dist: coverage; extra == "dev"
Requires-Dist: twine; extra == "dev"
